{
  "relationships_unfollowed_users": [
    {
      "title": "",
      "media_list_data": [
        
      ],
      "string_list_data": [
        {
          "href": "https://www.instagram.com/themillionairemagnets",
          "value": "themillionairemagnets",
          "timestamp": 1727076645
        }
      ]
    },
    {
      "title": "",
      "media_list_data": [
        
      ],
      "string_list_data": [
        {
          "href": "https://www.instagram.com/donato.lorena",
          "value": "donato.lorena",
          "timestamp": 1726877535
        }
      ]
    },
    {
      "title": "",
      "media_list_data": [
        
      ],
      "string_list_data": [
        {
          "href": "https://www.instagram.com/itsthemthighs",
          "value": "itsthemthighs",
          "timestamp": 1726764799
        }
      ]
    },
    {
      "title": "",
      "media_list_data": [
        
      ],
      "string_list_data": [
        {
          "href": "https://www.instagram.com/ashley_uyen",
          "value": "ashley_uyen",
          "timestamp": 1726764797
        }
      ]
    },
    {
      "title": "",
      "media_list_data": [
        
      ],
      "string_list_data": [
        {
          "href": "https://www.instagram.com/m_pnguyen_",
          "value": "m_pnguyen_",
          "timestamp": 1726764795
        }
      ]
    },
    {
      "title": "",
      "media_list_data": [
        
      ],
      "string_list_data": [
        {
          "href": "https://www.instagram.com/tuyetel",
          "value": "tuyetel",
          "timestamp": 1726764794
        }
      ]
    },
    {
      "title": "",
      "media_list_data": [
        
      ],
      "string_list_data": [
        {
          "href": "https://www.instagram.com/shalombarile",
          "value": "shalombarile",
          "timestamp": 1726741604
        }
      ]
    },
    {
      "title": "",
      "media_list_data": [
        
      ],
      "string_list_data": [
        {
          "href": "https://www.instagram.com/christina_yim1",
          "value": "christina_yim1",
          "timestamp": 1726666793
        }
      ]
    },
    {
      "title": "",
      "media_list_data": [
        
      ],
      "string_list_data": [
        {
          "href": "https://www.instagram.com/layla.cooperrrr",
          "value": "layla.cooperrrr",
          "timestamp": 1726599466
        }
      ]
    },
    {
      "title": "",
      "media_list_data": [
        
      ],
      "string_list_data": [
        {
          "href": "https://www.instagram.com/aemcnelis",
          "value": "aemcnelis",
          "timestamp": 1726175575
        }
      ]
    },
    {
      "title": "",
      "media_list_data": [
        
      ],
      "string_list_data": [
        {
          "href": "https://www.instagram.com/jesikamadds",
          "value": "jesikamadds",
          "timestamp": 1726175550
        }
      ]
    },
    {
      "title": "",
      "media_list_data": [
        
      ],
      "string_list_data": [
        {
          "href": "https://www.instagram.com/ashleynikkolex",
          "value": "ashleynikkolex",
          "timestamp": 1725337729
        }
      ]
    },
    {
      "title": "",
      "media_list_data": [
        
      ],
      "string_list_data": [
        {
          "href": "https://www.instagram.com/clariibellareeve",
          "value": "clariibellareeve",
          "timestamp": 1725207290
        }
      ]
    },
    {
      "title": "",
      "media_list_data": [
        
      ],
      "string_list_data": [
        {
          "href": "https://www.instagram.com/jodi.in.nc",
          "value": "jodi.in.nc",
          "timestamp": 1724885530
        }
      ]
    },
    {
      "title": "",
      "media_list_data": [
        
      ],
      "string_list_data": [
        {
          "href": "https://www.instagram.com/anqxlina",
          "value": "anqxlina",
          "timestamp": 1724636900
        }
      ]
    },
    {
      "title": "",
      "media_list_data": [
        
      ],
      "string_list_data": [
        {
          "href": "https://www.instagram.com/onlyqualityvibesrunclub",
          "value": "onlyqualityvibesrunclub",
          "timestamp": 1724335064
        }
      ]
    },
    {
      "title": "",
      "media_list_data": [
        
      ],
      "string_list_data": [
        {
          "href": "https://www.instagram.com/gr_acemia8371",
          "value": "gr_acemia8371",
          "timestamp": 1724102326
        }
      ]
    },
    {
      "title": "",
      "media_list_data": [
        
      ],
      "string_list_data": [
        {
          "href": "https://www.instagram.com/jessiesantos",
          "value": "jessiesantos",
          "timestamp": 1723594586
        }
      ]
    },
    {
      "title": "",
      "media_list_data": [
        
      ],
      "string_list_data": [
        {
          "href": "https://www.instagram.com/jvliamorrie",
          "value": "jvliamorrie",
          "timestamp": 1723207578
        }
      ]
    },
    {
      "title": "",
      "media_list_data": [
        
      ],
      "string_list_data": [
        {
          "href": "https://www.instagram.com/jacob.songco",
          "value": "jacob.songco",
          "timestamp": 1722853695
        }
      ]
    },
    {
      "title": "",
      "media_list_data": [
        
      ],
      "string_list_data": [
        {
          "href": "https://www.instagram.com/goodindiesongs",
          "value": "goodindiesongs",
          "timestamp": 1722524891
        }
      ]
    },
    {
      "title": "",
      "media_list_data": [
        
      ],
      "string_list_data": [
        {
          "href": "https://www.instagram.com/2jointsshorts",
          "value": "2jointsshorts",
          "timestamp": 1722479986
        }
      ]
    }
  ]
}